cloudflare_saas/__init__.py
cloudflare_saas/cloudflare_client.py
cloudflare_saas/config.py
cloudflare_saas/dns_verifier.py
cloudflare_saas/exceptions.py
cloudflare_saas/logging_config.py
cloudflare_saas/models.py
cloudflare_saas/platform.py
cloudflare_saas/postgres_adapter.py
cloudflare_saas/r2_client.py
cloudflare_saas/storage_adapter.py
cloudflare_saas/terraform_deployer.py
cloudflare_saas/worker_template.js
cloudflare_saas-1.0.1.dist-info/METADATA
cloudflare_saas-1.0.1.dist-info/WHEEL
cloudflare_saas-1.0.1.dist-info/top_level.txt
cloudflare_saas-1.0.1.dist-info/RECORD
