Metadata-Version: 2.4
Name: cloudflare-saas
Version: 1.0.1
Summary: Production-ready async library for multi-tenant SaaS platforms with Cloudflare R2 and Workers
Home-page: https://github.com/innerkorehq/cloudflare-saas
Author: innerkore
Classifier: Development Status :: 4 - Beta
Classifier: Intended Audience :: Developers
Classifier: Topic :: Software Development :: Libraries :: Python Modules
Classifier: License :: OSI Approved :: MIT License
Classifier: Programming Language :: Python :: 3
Classifier: Programming Language :: Python :: 3.8
Classifier: Programming Language :: Python :: 3.9
Classifier: Programming Language :: Python :: 3.10
Classifier: Programming Language :: Python :: 3.11
Classifier: Programming Language :: Python :: 3.12
Requires-Python: >=3.8
Requires-Dist: cloudflare>=4.0.0
Requires-Dist: aioboto3>=12.0.0
Requires-Dist: aiodns>=3.1.0
Requires-Dist: pydantic>=2.0.0
Requires-Dist: python-terraform>=0.10.1
Requires-Dist: httpx>=0.25.0
Requires-Dist: tenacity>=8.2.0
Requires-Dist: asyncpg>=0.29.0
Requires-Dist: pycares>=4.3.0
Requires-Dist: botocore>=1.31.0
Provides-Extra: dev
Requires-Dist: pytest>=7.4.0; extra == "dev"
Requires-Dist: pytest-asyncio>=0.21.0; extra == "dev"
Requires-Dist: pytest-cov>=4.1.0; extra == "dev"
Requires-Dist: black>=23.0.0; extra == "dev"
Requires-Dist: mypy>=1.5.0; extra == "dev"
Requires-Dist: ruff>=0.1.0; extra == "dev"
Requires-Dist: bumpversion>=0.6.0; extra == "dev"
Provides-Extra: web
Requires-Dist: fastapi>=0.104.0; extra == "web"
Requires-Dist: uvicorn[standard]>=0.24.0; extra == "web"
Dynamic: author
Dynamic: classifier
Dynamic: description
Dynamic: description-content-type
Dynamic: home-page
Dynamic: provides-extra
Dynamic: requires-dist
Dynamic: requires-python
Dynamic: summary
